royce_bulksms/__init__.py
royce_bulksms/bulksms.py
python_royce_bulksms-1.1.dist-info/LICENSE
python_royce_bulksms-1.1.dist-info/METADATA
python_royce_bulksms-1.1.dist-info/WHEEL
python_royce_bulksms-1.1.dist-info/top_level.txt
python_royce_bulksms-1.1.dist-info/RECORD
