Metadata-Version: 2.1
Name: python-royce-bulksms
Version: 1.1
Summary: Kenya Bulksms gateway to Integrate bulksms into Python project in under 2 minutes.
Home-page: https://github.com/royceltd/python-royce-bulksms
Author: Royce Ltd
Author-email: developer@roycetechnologies.co.ke
Project-URL: Bug Tracker, https://github.com/royceltd/python-royce-bulksms/issues
Classifier: Programming Language :: Python :: 3
Classifier: License :: OSI Approved :: MIT License
Classifier: Operating System :: OS Independent
Requires-Python: >=3.6
License-File: LICENSE
